MANIFEST.in
README.txt
setup.cfg
setup.py
d9t/__init__.py
d9t.gis.egg-info/PKG-INFO
d9t.gis.egg-info/SOURCES.txt
d9t.gis.egg-info/dependency_links.txt
d9t.gis.egg-info/entry_points.txt
d9t.gis.egg-info/namespace_packages.txt
d9t.gis.egg-info/not-zip-safe
d9t.gis.egg-info/paster_plugins.txt
d9t.gis.egg-info/requires.txt
d9t.gis.egg-info/top_level.txt
d9t/gis/README.txt
d9t/gis/__init__.py
d9t/gis/configure.zcml
d9t/gis/coordinate.py
d9t/gis/coordinate_providers.py
d9t/gis/distance.py
d9t/gis/interfaces.py
d9t/gis/tests.py
d9t/gis/data/DE.csv
d9t/gis/data/original/DE.csv
docs/AUTHOR.txt
docs/HISTORY.txt
docs/INSTALL.txt
docs/LICENSE.txt