Metadata-Version: 1.1
Name: d9t.gis
Version: 0.4
Summary: GIS Tools
Home-page: http://d9t.de/
Author: Daniel Kraft
Author-email: dk@d9t.de
License: GPLv3
Platform: UNKNOWN
Classifier: Framework :: Zope3
Classifier: Programming Language :: Python
Classifier: Topic :: Software Development :: Libraries :: Python Modules
